django_env_overrides/__init__.py
django_env_overrides-0.1.0.dist-info/DESCRIPTION.rst
django_env_overrides-0.1.0.dist-info/METADATA
django_env_overrides-0.1.0.dist-info/RECORD
django_env_overrides-0.1.0.dist-info/WHEEL
django_env_overrides-0.1.0.dist-info/metadata.json
django_env_overrides-0.1.0.dist-info/top_level.txt
